{
	"references":[
		""
	],
	"software":[
		"https:\/\/doi.org\/10.5281\/zenodo.15920400"
	],
	"mult_tab":[
		[
			[
				1,
				0,
				0,
				0,
				0
			],
			[
				0,
				1,
				0,
				0,
				0
			],
			[
				0,
				0,
				1,
				0,
				0
			],
			[
				0,
				0,
				0,
				1,
				0
			],
			[
				0,
				0,
				0,
				0,
				1
			]
		],
		[
			[
				0,
				1,
				0,
				0,
				0
			],
			[
				1,
				5,
				0,
				0,
				1
			],
			[
				0,
				0,
				2,
				2,
				2
			],
			[
				0,
				0,
				2,
				3,
				3
			],
			[
				0,
				1,
				2,
				3,
				5
			]
		],
		[
			[
				0,
				0,
				1,
				0,
				0
			],
			[
				0,
				0,
				2,
				2,
				2
			],
			[
				1,
				2,
				0,
				9,
				1
			],
			[
				0,
				2,
				9,
				0,
				6
			],
			[
				0,
				2,
				1,
				6,
				10
			]
		],
		[
			[
				0,
				0,
				0,
				1,
				0
			],
			[
				0,
				0,
				2,
				3,
				3
			],
			[
				0,
				2,
				9,
				0,
				6
			],
			[
				1,
				3,
				0,
				12,
				6
			],
			[
				0,
				3,
				6,
				6,
				13
			]
		],
		[
			[
				0,
				0,
				0,
				0,
				1
			],
			[
				0,
				1,
				2,
				3,
				5
			],
			[
				0,
				2,
				1,
				6,
				10
			],
			[
				0,
				3,
				6,
				6,
				13
			],
			[
				1,
				5,
				10,
				13,
				13
			]
		]
	],
	"texnames":[
		"\\text{FR}^{5,13,0}_{455}"
	],
	"barcode":[
		1,
		3,
		1,
		7,
		8,
		8,
		1,
		8,
		6,
		4,
		8,
		7,
		2,
		1,
		4,
		1,
		5,
		3,
		0,
		1,
		5,
		0,
		1,
		5,
		4,
		3,
		3,
		8,
		4,
		9,
		5,
		2,
		4,
		7,
		8,
		8,
		7,
		9,
		8,
		4,
		7,
		1,
		5,
		7,
		5,
		2,
		7,
		6,
		4,
		0,
		9,
		5,
		7,
		4,
		1,
		8,
		8,
		6,
		3,
		4,
		4,
		9,
		3,
		7,
		8,
		2,
		0,
		2,
		3,
		0,
		1,
		6,
		0,
		1,
		4,
		7,
		0,
		0,
		4,
		5,
		7,
		6,
		7,
		9,
		5,
		1,
		3,
		8,
		6,
		6,
		4,
		2,
		5,
		7,
		3,
		6,
		1,
		7,
		8,
		4,
		8,
		8,
		6,
		1,
		8,
		4,
		8,
		2,
		1,
		1,
		5,
		3,
		3,
		0,
		8,
		8,
		0,
		0,
		0,
		0,
		8,
		6,
		0,
		7,
		9,
		9,
		9,
		7,
		2,
		1,
		4,
		6,
		8,
		9,
		6,
		2,
		3,
		0,
		4,
		3,
		6,
		2,
		4
	],
	"formal_code":[
		5,
		13,
		0,
		455
	],
	"tensor_product_decompositions":{
		"identifiers":[
			"formal_code"
		],
		"value":[]
	},
	"sub_fusion_rings":{
		"identifiers":[
			"injection",
			"formal_code"
		],
		"value":[]
	},
	"numeric_characters":[
		[
			[
				1.0,
				0
			],
			[
				8.545487227227646,
				0
			],
			[
				1.5503475011527401e1,
				0
			],
			[
				2.1440983018225186e1,
				0
			],
			[
				2.9297915814572605e1,
				0
			]
		],
		[
			[
				1.0,
				0
			],
			[
				1.1290622808464332,
				0
			],
			[
				5.115871285751636,
				0
			],
			[
				3.1427271356541384,
				0
			],
			[
				-5.370529770202016,
				0
			]
		],
		[
			[
				1.0,
				0
			],
			[
				0.3856844315774882,
				0
			],
			[
				-9.731527693622184,
				0
			],
			[
				1.0634548007300747e1,
				0
			],
			[
				-2.779669677126191,
				0
			]
		],
		[
			[
				1.0,
				0
			],
			[
				-0.20877984232510452,
				0
			],
			[
				-1.1832129131100351e-2,
				0
			],
			[
				-7.442095002853712e-2,
				0
			],
			[
				8.748823418681817e-2,
				0
			]
		],
		[
			[
				1.0,
				0
			],
			[
				5.148545902673538,
				0
			],
			[
				-0.8759864745257534,
				0
			],
			[
				-1.1438372111515336,
				0
			],
			[
				-0.23520460143121555,
				0
			]
		]
	],
	"numeric_frobenius_perron_dimensions":[
		1.0,
		8.545487227227644,
		1.5503475011527401e1,
		2.1440983018225186e1,
		2.9297915814572605e1
	],
	"numeric_frobenius_perron_dimension":1.6324667132493696e3,
	"info":"Fusion ring. mult_tab provides structure constants. barcode and formal_code provide unique identifiers see (DOI: 10.1063\/5.0148848). sub_fusion_rings provides tuples where the first element corresponds to the elements of the ring that form the subring isomorphic to the ring identified by the second element of the tuple. software provides doi of original software used to represent fusion ring.",
	"comments":[
		""
	]
}