{
	"references":[
		""
	],
	"software":[
		"https:\/\/doi.org\/10.5281\/zenodo.15920400"
	],
	"mult_tab":[
		[
			[
				1,
				0,
				0,
				0,
				0
			],
			[
				0,
				1,
				0,
				0,
				0
			],
			[
				0,
				0,
				1,
				0,
				0
			],
			[
				0,
				0,
				0,
				1,
				0
			],
			[
				0,
				0,
				0,
				0,
				1
			]
		],
		[
			[
				0,
				1,
				0,
				0,
				0
			],
			[
				1,
				2,
				4,
				0,
				3
			],
			[
				0,
				4,
				3,
				2,
				5
			],
			[
				0,
				0,
				2,
				7,
				5
			],
			[
				0,
				3,
				5,
				5,
				4
			]
		],
		[
			[
				0,
				0,
				1,
				0,
				0
			],
			[
				0,
				4,
				3,
				2,
				5
			],
			[
				1,
				3,
				8,
				5,
				5
			],
			[
				0,
				2,
				5,
				9,
				7
			],
			[
				0,
				5,
				5,
				7,
				9
			]
		],
		[
			[
				0,
				0,
				0,
				1,
				0
			],
			[
				0,
				0,
				2,
				7,
				5
			],
			[
				0,
				2,
				5,
				9,
				7
			],
			[
				1,
				7,
				9,
				4,
				9
			],
			[
				0,
				5,
				7,
				9,
				9
			]
		],
		[
			[
				0,
				0,
				0,
				0,
				1
			],
			[
				0,
				3,
				5,
				5,
				4
			],
			[
				0,
				5,
				5,
				7,
				9
			],
			[
				0,
				5,
				7,
				9,
				9
			],
			[
				1,
				4,
				9,
				9,
				10
			]
		]
	],
	"texnames":[
		"\\text{FR}^{5,10,0}_{81}"
	],
	"barcode":[
		1,
		3,
		5,
		7,
		3,
		5,
		4,
		2,
		4,
		2,
		7,
		5,
		2,
		9,
		3,
		3,
		8,
		1,
		9,
		3,
		4,
		5,
		1,
		1,
		6,
		7,
		9,
		7,
		8,
		9,
		8,
		8,
		3,
		9,
		7,
		7,
		8,
		7,
		1,
		6,
		3,
		3,
		4,
		0,
		9,
		2,
		8,
		2,
		0,
		4,
		7,
		3,
		8,
		1,
		9,
		9,
		3,
		3,
		3,
		4,
		1,
		1,
		2,
		6,
		5,
		4,
		9,
		0,
		8,
		4,
		9,
		7,
		8,
		5,
		7,
		2,
		6,
		1,
		6,
		1,
		6,
		3,
		3,
		2,
		5,
		1,
		2,
		2,
		5,
		7,
		8,
		2,
		1,
		9,
		6,
		9,
		8,
		4,
		0,
		3,
		2,
		9,
		0,
		2,
		8,
		2,
		3,
		8,
		3,
		9,
		7,
		8,
		3,
		3,
		6,
		5,
		0,
		9,
		9,
		5,
		9,
		5,
		2,
		2,
		8,
		8,
		0,
		7,
		5,
		2
	],
	"formal_code":[
		5,
		10,
		0,
		81
	],
	"tensor_product_decompositions":{
		"identifiers":[
			"formal_code"
		],
		"value":[]
	},
	"sub_fusion_rings":{
		"identifiers":[
			"injection",
			"formal_code"
		],
		"value":[]
	},
	"numeric_characters":[
		[
			[
				1.0,
				0
			],
			[
				1.4145876696121222e1,
				0
			],
			[
				2.201792530971463e1,
				0
			],
			[
				2.5460809518696784e1,
				0
			],
			[
				2.7580790956921497e1,
				0
			]
		],
		[
			[
				1.0,
				0
			],
			[
				5.483324488566845,
				0
			],
			[
				4.111858353109738,
				0
			],
			[
				-7.238413920689428,
				0
			],
			[
				0.5509216857814052,
				0
			]
		],
		[
			[
				1.0,
				0
			],
			[
				-2.1847421826044835,
				0
			],
			[
				4.029854673135121,
				0
			],
			[
				0.5699688774909967,
				0
			],
			[
				-2.6589453076267056,
				0
			]
		],
		[
			[
				1.0,
				0
			],
			[
				0.2805156665895782,
				0
			],
			[
				-0.23968638482956306,
				0
			],
			[
				0.20121097994098996,
				0
			],
			[
				-0.17453225155290292,
				0
			]
		],
		[
			[
				1.0,
				0
			],
			[
				-1.7249746686731622,
				0
			],
			[
				8.004804887007244e-2,
				0
			],
			[
				-0.9935754554393442,
				0
			],
			[
				1.7017649164767066,
				0
			]
		]
	],
	"numeric_frobenius_perron_dimensions":[
		1.0,
		1.4145876696121222e1,
		2.201792530971463e1,
		2.5460809518696784e1,
		2.7580790956921497e1
	],
	"numeric_frobenius_perron_dimension":2.094847713602801e3,
	"info":"Fusion ring. mult_tab provides structure constants. barcode and formal_code provide unique identifiers see (DOI: 10.1063\/5.0148848). sub_fusion_rings provides tuples where the first element corresponds to the elements of the ring that form the subring isomorphic to the ring identified by the second element of the tuple. software provides doi of original software used to represent fusion ring.",
	"comments":[
		""
	]
}