{
	"references":[
		""
	],
	"software":[
		"https:\/\/doi.org\/10.5281\/zenodo.15920400"
	],
	"mult_tab":[
		[
			[
				1,
				0,
				0,
				0,
				0
			],
			[
				0,
				1,
				0,
				0,
				0
			],
			[
				0,
				0,
				1,
				0,
				0
			],
			[
				0,
				0,
				0,
				1,
				0
			],
			[
				0,
				0,
				0,
				0,
				1
			]
		],
		[
			[
				0,
				1,
				0,
				0,
				0
			],
			[
				1,
				8,
				0,
				3,
				1
			],
			[
				0,
				0,
				7,
				4,
				4
			],
			[
				0,
				3,
				4,
				8,
				2
			],
			[
				0,
				1,
				4,
				2,
				10
			]
		],
		[
			[
				0,
				0,
				1,
				0,
				0
			],
			[
				0,
				0,
				7,
				4,
				4
			],
			[
				1,
				7,
				9,
				5,
				9
			],
			[
				0,
				4,
				5,
				8,
				12
			],
			[
				0,
				4,
				9,
				12,
				8
			]
		],
		[
			[
				0,
				0,
				0,
				1,
				0
			],
			[
				0,
				3,
				4,
				8,
				2
			],
			[
				0,
				4,
				5,
				8,
				12
			],
			[
				1,
				8,
				8,
				6,
				10
			],
			[
				0,
				2,
				12,
				10,
				9
			]
		],
		[
			[
				0,
				0,
				0,
				0,
				1
			],
			[
				0,
				1,
				4,
				2,
				10
			],
			[
				0,
				4,
				9,
				12,
				8
			],
			[
				0,
				2,
				12,
				10,
				9
			],
			[
				1,
				10,
				8,
				9,
				13
			]
		]
	],
	"texnames":[
		"\\text{FR}^{5,13,0}_{343}"
	],
	"barcode":[
		1,
		3,
		1,
		7,
		8,
		8,
		1,
		8,
		6,
		4,
		8,
		7,
		2,
		1,
		4,
		1,
		5,
		3,
		0,
		1,
		5,
		0,
		1,
		5,
		4,
		3,
		3,
		8,
		4,
		9,
		5,
		2,
		4,
		7,
		8,
		9,
		3,
		0,
		9,
		7,
		6,
		6,
		2,
		6,
		9,
		7,
		9,
		2,
		8,
		6,
		4,
		1,
		2,
		8,
		2,
		1,
		6,
		4,
		8,
		6,
		2,
		5,
		5,
		8,
		9,
		6,
		3,
		0,
		3,
		9,
		4,
		3,
		1,
		9,
		3,
		6,
		2,
		7,
		2,
		1,
		7,
		7,
		4,
		2,
		7,
		9,
		9,
		6,
		2,
		2,
		2,
		4,
		6,
		9,
		1,
		9,
		7,
		0,
		6,
		2,
		5,
		2,
		7,
		0,
		1,
		3,
		1,
		7,
		7,
		7,
		7,
		3,
		6,
		3,
		2,
		9,
		1,
		9,
		1,
		0,
		4,
		1,
		1,
		6,
		6,
		9,
		9,
		3,
		5,
		4,
		9,
		8,
		0,
		7,
		3,
		9,
		7,
		8,
		9,
		9,
		7,
		9,
		8
	],
	"formal_code":[
		5,
		13,
		0,
		343
	],
	"tensor_product_decompositions":{
		"identifiers":[
			"formal_code"
		],
		"value":[]
	},
	"sub_fusion_rings":{
		"identifiers":[
			"injection",
			"formal_code"
		],
		"value":[]
	},
	"numeric_characters":[
		[
			[
				1.0,
				0
			],
			[
				1.5733890880335798e1,
				0
			],
			[
				2.8438862208034497e1,
				0
			],
			[
				2.9294357685078943e1,
				0
			],
			[
				3.280112213639077e1,
				0
			]
		],
		[
			[
				1.0,
				0
			],
			[
				6.209151877168238,
				0
			],
			[
				-5.551181421939632,
				0
			],
			[
				-6.608591667681963,
				0
			],
			[
				7.70612701944184,
				0
			]
		],
		[
			[
				1.0,
				0
			],
			[
				8.923797232853891,
				0
			],
			[
				-2.856439075872061,
				0
			],
			[
				4.308790793877116,
				0
			],
			[
				-5.682593191371715,
				0
			]
		],
		[
			[
				1.0,
				0
			],
			[
				2.2875975856701674,
				0
			],
			[
				5.025242922017942,
				0
			],
			[
				-4.073718125909774,
				0
			],
			[
				-1.8465235936680398,
				0
			]
		],
		[
			[
				1.0,
				0
			],
			[
				-0.15443757602809388,
				0
			],
			[
				-5.6484632240744e-2,
				0
			],
			[
				7.916131463567878e-2,
				0
			],
			[
				2.1867629207147923e-2,
				0
			]
		]
	],
	"numeric_frobenius_perron_dimensions":[
		1.0,
		1.5733890880335789e1,
		2.8438862208034497e1,
		2.9294357685078943e1,
		3.280112213639077e1
	],
	"numeric_frobenius_perron_dimension":2.991397211509655e3,
	"info":"Fusion ring. mult_tab provides structure constants. barcode and formal_code provide unique identifiers see (DOI: 10.1063\/5.0148848). sub_fusion_rings provides tuples where the first element corresponds to the elements of the ring that form the subring isomorphic to the ring identified by the second element of the tuple. software provides doi of original software used to represent fusion ring.",
	"comments":[
		""
	]
}