{
	"references":[
		""
	],
	"software":[
		"https:\/\/doi.org\/10.5281\/zenodo.15920400"
	],
	"mult_tab":[
		[
			[
				1,
				0,
				0,
				0,
				0
			],
			[
				0,
				1,
				0,
				0,
				0
			],
			[
				0,
				0,
				1,
				0,
				0
			],
			[
				0,
				0,
				0,
				1,
				0
			],
			[
				0,
				0,
				0,
				0,
				1
			]
		],
		[
			[
				0,
				1,
				0,
				0,
				0
			],
			[
				1,
				11,
				0,
				1,
				6
			],
			[
				0,
				0,
				13,
				6,
				3
			],
			[
				0,
				1,
				6,
				12,
				6
			],
			[
				0,
				6,
				3,
				6,
				13
			]
		],
		[
			[
				0,
				0,
				1,
				0,
				0
			],
			[
				0,
				0,
				13,
				6,
				3
			],
			[
				1,
				13,
				7,
				4,
				11
			],
			[
				0,
				6,
				4,
				12,
				15
			],
			[
				0,
				3,
				11,
				15,
				11
			]
		],
		[
			[
				0,
				0,
				0,
				1,
				0
			],
			[
				0,
				1,
				6,
				12,
				6
			],
			[
				0,
				6,
				4,
				12,
				15
			],
			[
				1,
				12,
				12,
				12,
				12
			],
			[
				0,
				6,
				15,
				12,
				16
			]
		],
		[
			[
				0,
				0,
				0,
				0,
				1
			],
			[
				0,
				6,
				3,
				6,
				13
			],
			[
				0,
				3,
				11,
				15,
				11
			],
			[
				0,
				6,
				15,
				12,
				16
			],
			[
				1,
				13,
				11,
				16,
				15
			]
		]
	],
	"texnames":[
		"\\text{FR}^{5,16,0}_{351}"
	],
	"barcode":[
		3,
		7,
		6,
		4,
		1,
		4,
		4,
		3,
		4,
		3,
		0,
		6,
		5,
		8,
		9,
		6,
		9,
		9,
		4,
		3,
		9,
		0,
		0,
		0,
		5,
		8,
		2,
		8,
		2,
		6,
		5,
		5,
		9,
		0,
		2,
		3,
		0,
		4,
		6,
		9,
		1,
		3,
		8,
		2,
		0,
		9,
		9,
		4,
		7,
		4,
		2,
		3,
		4,
		6,
		0,
		9,
		5,
		8,
		7,
		1,
		9,
		1,
		6,
		6,
		9,
		4,
		4,
		9,
		8,
		0,
		2,
		0,
		1,
		8,
		5,
		6,
		3,
		9,
		3,
		1,
		6,
		4,
		8,
		7,
		2,
		7,
		5,
		4,
		6,
		8,
		3,
		1,
		6,
		0,
		4,
		4,
		9,
		1,
		6,
		5,
		3,
		5,
		4,
		8,
		9,
		5,
		6,
		7,
		0,
		1,
		6,
		7,
		1,
		0,
		9,
		5,
		4,
		4,
		6,
		1,
		1,
		4,
		9,
		2,
		6,
		1,
		7,
		7,
		4,
		8,
		4,
		5,
		1,
		7,
		4,
		6,
		7,
		4,
		4,
		2,
		0,
		2,
		9,
		9,
		4,
		7,
		6,
		7,
		6,
		7,
		8,
		3,
		5
	],
	"formal_code":[
		5,
		16,
		0,
		351
	],
	"tensor_product_decompositions":{
		"identifiers":[
			"formal_code"
		],
		"value":[]
	},
	"sub_fusion_rings":{
		"identifiers":[
			"injection",
			"formal_code"
		],
		"value":[]
	},
	"numeric_characters":[
		[
			[
				1.0,
				0
			],
			[
				2.4065287464905488e1,
				0
			],
			[
				3.49877961640841e1,
				0
			],
			[
				4.189819508942177e1,
				0
			],
			[
				4.525361726085919e1,
				0
			]
		],
		[
			[
				1.0,
				0
			],
			[
				4.185089513699938,
				0
			],
			[
				-1.4315477579534392,
				0
			],
			[
				4.978085554496761,
				0
			],
			[
				-5.749849327919149,
				0
			]
		],
		[
			[
				1.0,
				0
			],
			[
				6.799281845748479,
				0
			],
			[
				9.076361470721297,
				0
			],
			[
				-7.545277455162977,
				0
			],
			[
				-3.669431538357575,
				0
			]
		],
		[
			[
				1.0,
				0
			],
			[
				1.4074843887257087e1,
				0
			],
			[
				-1.2626338096010706e1,
				0
			],
			[
				-6.31096657570064,
				0
			],
			[
				8.098152377755147,
				0
			]
		],
		[
			[
				1.0,
				0
			],
			[
				-0.12450271161099367,
				0
			],
			[
				-6.271780841254927e-3,
				0
			],
			[
				-2.0036613054914575e-2,
				0
			],
			[
				6.75112276623892e-2,
				0
			]
		]
	],
	"numeric_frobenius_perron_dimensions":[
		1.0,
		2.4065287464905484e1,
		3.49877961640841e1,
		4.189819508942177e1,
		4.525361726085919e1
	],
	"numeric_frobenius_perron_dimension":5.607632568131614e3,
	"info":"Fusion ring. mult_tab provides structure constants. barcode and formal_code provide unique identifiers see (DOI: 10.1063\/5.0148848). sub_fusion_rings provides tuples where the first element corresponds to the elements of the ring that form the subring isomorphic to the ring identified by the second element of the tuple. software provides doi of original software used to represent fusion ring.",
	"comments":[
		""
	]
}