{
	"references":[
		""
	],
	"software":[
		"https:\/\/doi.org\/10.5281\/zenodo.15920400"
	],
	"mult_tab":[
		[
			[
				1,
				0,
				0,
				0,
				0
			],
			[
				0,
				1,
				0,
				0,
				0
			],
			[
				0,
				0,
				1,
				0,
				0
			],
			[
				0,
				0,
				0,
				1,
				0
			],
			[
				0,
				0,
				0,
				0,
				1
			]
		],
		[
			[
				0,
				1,
				0,
				0,
				0
			],
			[
				1,
				0,
				0,
				0,
				0
			],
			[
				0,
				0,
				1,
				0,
				0
			],
			[
				0,
				0,
				0,
				1,
				0
			],
			[
				0,
				0,
				0,
				0,
				1
			]
		],
		[
			[
				0,
				0,
				1,
				0,
				0
			],
			[
				0,
				0,
				1,
				0,
				0
			],
			[
				1,
				1,
				14,
				1,
				0
			],
			[
				0,
				0,
				1,
				14,
				1
			],
			[
				0,
				0,
				0,
				1,
				15
			]
		],
		[
			[
				0,
				0,
				0,
				1,
				0
			],
			[
				0,
				0,
				0,
				1,
				0
			],
			[
				0,
				0,
				1,
				14,
				1
			],
			[
				1,
				1,
				14,
				0,
				15
			],
			[
				0,
				0,
				1,
				15,
				14
			]
		],
		[
			[
				0,
				0,
				0,
				0,
				1
			],
			[
				0,
				0,
				0,
				0,
				1
			],
			[
				0,
				0,
				0,
				1,
				15
			],
			[
				0,
				0,
				1,
				15,
				14
			],
			[
				1,
				1,
				15,
				14,
				14
			]
		]
	],
	"texnames":[
		"\\text{FR}^{5,15,0}_{1403}"
	],
	"barcode":[
		2,
		0,
		4,
		5,
		8,
		6,
		9,
		2,
		5,
		1,
		8,
		7,
		8,
		3,
		9,
		8,
		6,
		8,
		3,
		8,
		6,
		4,
		3,
		6,
		6,
		2,
		8,
		4,
		5,
		9,
		5,
		4,
		2,
		6,
		4,
		9,
		8,
		9,
		4,
		6,
		7,
		2,
		0,
		8,
		3,
		2,
		8,
		8,
		6,
		8,
		9,
		5,
		1,
		8,
		6,
		5,
		4,
		5,
		2,
		2,
		2,
		8,
		9,
		3,
		9,
		8,
		1,
		6,
		9,
		6,
		4,
		9,
		5,
		2,
		3,
		7,
		6,
		4,
		6,
		3,
		0,
		5,
		2,
		8,
		2,
		2,
		8,
		1,
		7,
		1,
		5,
		1,
		1,
		9,
		3,
		8,
		7,
		7,
		8,
		4,
		7,
		9,
		9,
		1,
		6,
		9,
		5,
		2,
		4,
		8,
		6,
		7,
		2,
		9,
		1,
		4,
		1,
		0,
		3,
		2,
		7,
		8,
		2,
		5,
		2,
		5,
		9,
		8,
		8,
		9,
		2,
		9,
		9,
		3,
		5,
		3,
		5,
		1,
		9,
		8,
		4,
		6,
		0,
		8,
		5,
		8,
		3,
		4,
		0,
		8
	],
	"formal_code":[
		5,
		15,
		0,
		1403
	],
	"tensor_product_decompositions":{
		"identifiers":[
			"formal_code"
		],
		"value":[]
	},
	"sub_fusion_rings":{
		"identifiers":[
			"injection",
			"formal_code"
		],
		"value":[
			[
				[
					1,
					2
				],
				[
					2,
					1,
					0,
					1
				]
			]
		]
	},
	"numeric_characters":[
		[
			[
				1.0,
				0
			],
			[
				1.0,
				0
			],
			[
				1.5816478370507069e1,
				0
			],
			[
				2.6730290857618975e1,
				0
			],
			[
				3.2738516809720636e1,
				0
			]
		],
		[
			[
				1.0,
				0
			],
			[
				1.0,
				0
			],
			[
				1.2804619822685929e1,
				0
			],
			[
				-1.730638871408157e1,
				0
			],
			[
				7.883094187019126,
				0
			]
		],
		[
			[
				1.0,
				0
			],
			[
				1.0,
				0
			],
			[
				1.4521037176743732e1,
				0
			],
			[
				5.566000213961327,
				0
			],
			[
				-1.1620944139506314e1,
				0
			]
		],
		[
			[
				1.0,
				0
			],
			[
				1.0,
				0
			],
			[
				-0.14213536993672987,
				0
			],
			[
				1.0097642501269263e-2,
				0
			],
			[
				-6.668572334465568e-4,
				0
			]
		],
		[
			[
				1.0,
				0
			],
			[
				-1.0,
				0
			],
			[
				0.0,
				0
			],
			[
				0.0,
				0
			],
			[
				0.0,
				0
			]
		]
	],
	"numeric_frobenius_perron_dimensions":[
		1.0,
		1.0,
		1.5816478370506902e1,
		2.6730290857618975e1,
		3.273851680972063e1
	],
	"numeric_frobenius_perron_dimension":2.0384799202779814e3,
	"info":"Fusion ring. mult_tab provides structure constants. barcode and formal_code provide unique identifiers see (DOI: 10.1063\/5.0148848). sub_fusion_rings provides tuples where the first element corresponds to the elements of the ring that form the subring isomorphic to the ring identified by the second element of the tuple. software provides doi of original software used to represent fusion ring.",
	"comments":[
		""
	]
}