{
	"references":[
		""
	],
	"software":[
		"https:\/\/doi.org\/10.5281\/zenodo.15920400"
	],
	"mult_tab":[
		[
			[
				1,
				0,
				0,
				0,
				0
			],
			[
				0,
				1,
				0,
				0,
				0
			],
			[
				0,
				0,
				1,
				0,
				0
			],
			[
				0,
				0,
				0,
				1,
				0
			],
			[
				0,
				0,
				0,
				0,
				1
			]
		],
		[
			[
				0,
				1,
				0,
				0,
				0
			],
			[
				1,
				3,
				1,
				1,
				2
			],
			[
				0,
				1,
				3,
				3,
				2
			],
			[
				0,
				1,
				3,
				4,
				4
			],
			[
				0,
				2,
				2,
				4,
				5
			]
		],
		[
			[
				0,
				0,
				1,
				0,
				0
			],
			[
				0,
				1,
				3,
				3,
				2
			],
			[
				1,
				3,
				5,
				4,
				2
			],
			[
				0,
				3,
				4,
				5,
				6
			],
			[
				0,
				2,
				2,
				6,
				8
			]
		],
		[
			[
				0,
				0,
				0,
				1,
				0
			],
			[
				0,
				1,
				3,
				4,
				4
			],
			[
				0,
				3,
				4,
				5,
				6
			],
			[
				1,
				4,
				5,
				8,
				8
			],
			[
				0,
				4,
				6,
				8,
				9
			]
		],
		[
			[
				0,
				0,
				0,
				0,
				1
			],
			[
				0,
				2,
				2,
				4,
				5
			],
			[
				0,
				2,
				2,
				6,
				8
			],
			[
				0,
				4,
				6,
				8,
				9
			],
			[
				1,
				5,
				8,
				9,
				8
			]
		]
	],
	"texnames":[
		"\\text{FR}^{5,9,0}_{549}"
	],
	"barcode":[
		1,
		0,
		0,
		0,
		0,
		0,
		1,
		0,
		0,
		0,
		0,
		0,
		1,
		0,
		0,
		0,
		0,
		0,
		1,
		0,
		0,
		0,
		0,
		0,
		1,
		0,
		1,
		0,
		0,
		0,
		1,
		8,
		8,
		5,
		4,
		0,
		8,
		9,
		6,
		4,
		0,
		5,
		6,
		4,
		3,
		0,
		4,
		4,
		3,
		1,
		0,
		0,
		1,
		0,
		0,
		0,
		8,
		9,
		6,
		4,
		1,
		9,
		8,
		8,
		5,
		0,
		6,
		8,
		2,
		2,
		0,
		4,
		5,
		2,
		2,
		0,
		0,
		0,
		1,
		0,
		0,
		5,
		6,
		4,
		3,
		0,
		6,
		8,
		2,
		2,
		1,
		4,
		2,
		5,
		3,
		0,
		3,
		2,
		3,
		1,
		0,
		0,
		0,
		0,
		1,
		0,
		4,
		4,
		3,
		1,
		0,
		4,
		5,
		2,
		2,
		0,
		3,
		2,
		3,
		1,
		1,
		1,
		2,
		1,
		3
	],
	"formal_code":[
		5,
		9,
		0,
		549
	],
	"tensor_product_decompositions":{
		"identifiers":[
			"formal_code"
		],
		"value":[]
	},
	"sub_fusion_rings":{
		"identifiers":[
			"injection",
			"formal_code"
		],
		"value":[]
	},
	"numeric_characters":[
		[
			[
				1.0,
				0
			],
			[
				1.0941541301090448e1,
				0
			],
			[
				1.5795804257418688e1,
				0
			],
			[
				2.220229635518119e1,
				0
			],
			[
				2.3947300763798406e1,
				0
			]
		],
		[
			[
				1.0,
				0
			],
			[
				2.851446479481525,
				0
			],
			[
				-0.9601782594535083,
				0
			],
			[
				-1.12269723253546,
				0
			],
			[
				0.32964153944598795,
				0
			]
		],
		[
			[
				1.0,
				0
			],
			[
				-4.019618483594798e-2,
				0
			],
			[
				-0.7948072867279856,
				0
			],
			[
				1.269777345557493,
				0
			],
			[
				-0.6763828855231488,
				0
			]
		],
		[
			[
				1.0,
				0
			],
			[
				1.7127659890295255,
				0
			],
			[
				4.675287278816931,
				0
			],
			[
				7.453156367447004e-2,
				0
			],
			[
				-3.9772747382018445,
				0
			]
		],
		[
			[
				1.0,
				0
			],
			[
				-0.46555758476554937,
				0
			],
			[
				0.2838940099458747,
				0
			],
			[
				-0.42390803187769405,
				0
			],
			[
				0.3767153204805995,
				0
			]
		]
	],
	"numeric_frobenius_perron_dimensions":[
		1.0,
		1.0941541301090446e1,
		1.5795804257418688e1,
		2.220229635518119e1,
		2.3947300763798406e1
	],
	"numeric_frobenius_perron_dimension":1.4366399354972662e3,
	"info":"Fusion ring. mult_tab provides structure constants. barcode and formal_code provide unique identifiers see (DOI: 10.1063\/5.0148848). sub_fusion_rings provides tuples where the first element corresponds to the elements of the ring that form the subring isomorphic to the ring identified by the second element of the tuple. software provides doi of original software used to represent fusion ring.",
	"comments":[
		""
	]
}