{
	"references":[
		""
	],
	"software":[
		"https:\/\/doi.org\/10.5281\/zenodo.15920400"
	],
	"mult_tab":[
		[
			[
				1,
				0,
				0,
				0,
				0
			],
			[
				0,
				1,
				0,
				0,
				0
			],
			[
				0,
				0,
				1,
				0,
				0
			],
			[
				0,
				0,
				0,
				1,
				0
			],
			[
				0,
				0,
				0,
				0,
				1
			]
		],
		[
			[
				0,
				1,
				0,
				0,
				0
			],
			[
				1,
				0,
				0,
				0,
				0
			],
			[
				0,
				0,
				1,
				0,
				0
			],
			[
				0,
				0,
				0,
				1,
				0
			],
			[
				0,
				0,
				0,
				0,
				1
			]
		],
		[
			[
				0,
				0,
				1,
				0,
				0
			],
			[
				0,
				0,
				1,
				0,
				0
			],
			[
				1,
				1,
				8,
				5,
				5
			],
			[
				0,
				0,
				5,
				11,
				7
			],
			[
				0,
				0,
				5,
				7,
				12
			]
		],
		[
			[
				0,
				0,
				0,
				1,
				0
			],
			[
				0,
				0,
				0,
				1,
				0
			],
			[
				0,
				0,
				5,
				11,
				7
			],
			[
				1,
				1,
				11,
				6,
				15
			],
			[
				0,
				0,
				7,
				15,
				11
			]
		],
		[
			[
				0,
				0,
				0,
				0,
				1
			],
			[
				0,
				0,
				0,
				0,
				1
			],
			[
				0,
				0,
				5,
				7,
				12
			],
			[
				0,
				0,
				7,
				15,
				11
			],
			[
				1,
				1,
				12,
				11,
				13
			]
		]
	],
	"texnames":[
		"\\text{FR}^{5,15,0}_{831}"
	],
	"barcode":[
		2,
		0,
		4,
		5,
		8,
		6,
		9,
		2,
		5,
		1,
		8,
		7,
		8,
		3,
		9,
		8,
		6,
		8,
		3,
		8,
		6,
		4,
		3,
		6,
		6,
		2,
		8,
		4,
		5,
		9,
		5,
		4,
		2,
		6,
		4,
		9,
		8,
		9,
		4,
		6,
		7,
		2,
		0,
		8,
		3,
		2,
		8,
		8,
		6,
		8,
		9,
		5,
		1,
		8,
		6,
		5,
		4,
		5,
		2,
		2,
		2,
		8,
		9,
		3,
		9,
		8,
		1,
		6,
		9,
		6,
		4,
		9,
		5,
		2,
		3,
		6,
		6,
		9,
		2,
		2,
		5,
		7,
		0,
		3,
		5,
		5,
		4,
		6,
		8,
		1,
		8,
		1,
		4,
		1,
		2,
		2,
		8,
		0,
		9,
		1,
		0,
		4,
		4,
		3,
		9,
		8,
		9,
		3,
		4,
		7,
		0,
		2,
		2,
		2,
		1,
		4,
		2,
		6,
		4,
		9,
		0,
		8,
		8,
		0,
		2,
		8,
		0,
		1,
		1,
		4,
		9,
		6,
		4,
		9,
		6,
		3,
		6,
		7,
		0,
		5,
		9,
		5,
		5,
		6,
		4,
		4,
		2,
		0,
		3,
		8
	],
	"formal_code":[
		5,
		15,
		0,
		831
	],
	"tensor_product_decompositions":{
		"identifiers":[
			"formal_code"
		],
		"value":[]
	},
	"sub_fusion_rings":{
		"identifiers":[
			"injection",
			"formal_code"
		],
		"value":[
			[
				[
					1,
					2
				],
				[
					2,
					1,
					0,
					1
				]
			]
		]
	},
	"numeric_characters":[
		[
			[
				1.0,
				0
			],
			[
				1.0,
				0
			],
			[
				2.2086641804107472e1,
				0
			],
			[
				3.003379352309048e1,
				0
			],
			[
				3.179152882692711e1,
				0
			]
		],
		[
			[
				1.0,
				0
			],
			[
				1.0,
				0
			],
			[
				4.368680861876525,
				0
			],
			[
				-8.588186176580493,
				0
			],
			[
				5.015371292163295,
				0
			]
		],
		[
			[
				1.0,
				0
			],
			[
				1.0,
				0
			],
			[
				4.89606076633242,
				0
			],
			[
				0.4513072133061342,
				0
			],
			[
				-3.8907222339140852,
				0
			]
		],
		[
			[
				1.0,
				0
			],
			[
				1.0,
				0
			],
			[
				-0.3513834323164159,
				0
			],
			[
				0.10308544018387764,
				0
			],
			[
				8.382211482368086e-2,
				0
			]
		],
		[
			[
				1.0,
				0
			],
			[
				-1.0,
				0
			],
			[
				0.0,
				0
			],
			[
				0.0,
				0
			],
			[
				0.0,
				0
			]
		]
	],
	"numeric_frobenius_perron_dimensions":[
		1.0,
		1.0,
		2.208664180410747e1,
		3.003379352309048e1,
		3.179152882692711e1
	],
	"numeric_frobenius_perron_dimension":2.402549804723917e3,
	"info":"Fusion ring. mult_tab provides structure constants. barcode and formal_code provide unique identifiers see (DOI: 10.1063\/5.0148848). sub_fusion_rings provides tuples where the first element corresponds to the elements of the ring that form the subring isomorphic to the ring identified by the second element of the tuple. software provides doi of original software used to represent fusion ring.",
	"comments":[
		""
	]
}