{
	"references":[
		""
	],
	"software":[
		"https:\/\/doi.org\/10.5281\/zenodo.15920400"
	],
	"mult_tab":[
		[
			[
				1,
				0,
				0,
				0,
				0
			],
			[
				0,
				1,
				0,
				0,
				0
			],
			[
				0,
				0,
				1,
				0,
				0
			],
			[
				0,
				0,
				0,
				1,
				0
			],
			[
				0,
				0,
				0,
				0,
				1
			]
		],
		[
			[
				0,
				1,
				0,
				0,
				0
			],
			[
				1,
				0,
				0,
				0,
				0
			],
			[
				0,
				0,
				1,
				0,
				0
			],
			[
				0,
				0,
				0,
				1,
				0
			],
			[
				0,
				0,
				0,
				0,
				1
			]
		],
		[
			[
				0,
				0,
				1,
				0,
				0
			],
			[
				0,
				0,
				1,
				0,
				0
			],
			[
				1,
				1,
				6,
				7,
				4
			],
			[
				0,
				0,
				7,
				8,
				4
			],
			[
				0,
				0,
				4,
				4,
				12
			]
		],
		[
			[
				0,
				0,
				0,
				1,
				0
			],
			[
				0,
				0,
				0,
				1,
				0
			],
			[
				0,
				0,
				7,
				8,
				4
			],
			[
				1,
				1,
				8,
				9,
				4
			],
			[
				0,
				0,
				4,
				4,
				14
			]
		],
		[
			[
				0,
				0,
				0,
				0,
				1
			],
			[
				0,
				0,
				0,
				0,
				1
			],
			[
				0,
				0,
				4,
				4,
				12
			],
			[
				0,
				0,
				4,
				4,
				14
			],
			[
				1,
				1,
				12,
				14,
				1
			]
		]
	],
	"texnames":[
		"\\text{FR}^{5,14,0}_{964}"
	],
	"barcode":[
		6,
		8,
		4,
		4,
		0,
		9,
		7,
		0,
		7,
		8,
		0,
		3,
		0,
		6,
		8,
		2,
		0,
		8,
		2,
		8,
		2,
		7,
		0,
		4,
		7,
		6,
		6,
		1,
		8,
		9,
		7,
		5,
		4,
		7,
		0,
		8,
		4,
		8,
		9,
		3,
		1,
		3,
		5,
		5,
		2,
		8,
		6,
		2,
		2,
		4,
		0,
		9,
		9,
		4,
		4,
		5,
		2,
		0,
		4,
		1,
		7,
		6,
		9,
		3,
		2,
		0,
		5,
		5,
		6,
		9,
		8,
		3,
		6,
		5,
		6,
		3,
		4,
		0,
		8,
		2,
		3,
		7,
		9,
		7,
		7,
		6,
		0,
		6,
		0,
		1,
		9,
		5,
		5,
		0,
		5,
		2,
		1,
		7,
		8,
		3,
		4,
		9,
		2,
		5,
		1,
		4,
		9,
		5,
		7,
		3,
		8,
		5,
		7,
		7,
		3,
		6,
		9,
		9,
		0,
		8,
		0,
		3,
		6,
		1,
		4,
		4,
		4,
		3,
		0,
		8,
		7,
		4,
		3,
		8,
		5,
		5,
		0,
		3,
		0,
		8,
		4,
		8,
		2,
		3,
		3,
		1
	],
	"formal_code":[
		5,
		14,
		0,
		964
	],
	"tensor_product_decompositions":{
		"identifiers":[
			"formal_code"
		],
		"value":[]
	},
	"sub_fusion_rings":{
		"identifiers":[
			"injection",
			"formal_code"
		],
		"value":[
			[
				[
					1,
					2
				],
				[
					2,
					1,
					0,
					1
				]
			]
		]
	},
	"numeric_characters":[
		[
			[
				1.0,
				0
			],
			[
				1.0,
				0
			],
			[
				1.8804062201237432e1,
				0
			],
			[
				2.0804062201237432e1,
				0
			],
			[
				2.328498666297993e1,
				0
			]
		],
		[
			[
				1.0,
				0
			],
			[
				1.0,
				0
			],
			[
				7.3531082701261665,
				0
			],
			[
				9.353108270126166,
				0
			],
			[
				-1.4380551569860586e1,
				0
			]
		],
		[
			[
				1.0,
				0
			],
			[
				1.0,
				0
			],
			[
				1.0,
				0
			],
			[
				-1.0,
				0
			],
			[
				0.0,
				0
			]
		],
		[
			[
				1.0,
				0
			],
			[
				1.0,
				0
			],
			[
				-1.157170471363598,
				0
			],
			[
				0.842829528636402,
				0
			],
			[
				9.556490688065637e-2,
				0
			]
		],
		[
			[
				1.0,
				0
			],
			[
				-1.0,
				0
			],
			[
				0.0,
				0
			],
			[
				0.0,
				0
			],
			[
				0.0,
				0
			]
		]
	],
	"numeric_frobenius_perron_dimensions":[
		1.0,
		1.0,
		1.8804062201237432e1,
		2.080406220123743e1,
		2.328498666297993e1
	],
	"numeric_frobenius_perron_dimension":1.3305923632361155e3,
	"info":"Fusion ring. mult_tab provides structure constants. barcode and formal_code provide unique identifiers see (DOI: 10.1063\/5.0148848). sub_fusion_rings provides tuples where the first element corresponds to the elements of the ring that form the subring isomorphic to the ring identified by the second element of the tuple. software provides doi of original software used to represent fusion ring.",
	"comments":[
		""
	]
}