{
	"references":[
		""
	],
	"software":[
		"https:\/\/doi.org\/10.5281\/zenodo.15920400"
	],
	"mult_tab":[
		[
			[
				1,
				0,
				0,
				0,
				0
			],
			[
				0,
				1,
				0,
				0,
				0
			],
			[
				0,
				0,
				1,
				0,
				0
			],
			[
				0,
				0,
				0,
				1,
				0
			],
			[
				0,
				0,
				0,
				0,
				1
			]
		],
		[
			[
				0,
				1,
				0,
				0,
				0
			],
			[
				1,
				8,
				2,
				2,
				2
			],
			[
				0,
				2,
				4,
				5,
				4
			],
			[
				0,
				2,
				5,
				8,
				2
			],
			[
				0,
				2,
				4,
				2,
				9
			]
		],
		[
			[
				0,
				0,
				1,
				0,
				0
			],
			[
				0,
				2,
				4,
				5,
				4
			],
			[
				1,
				4,
				2,
				6,
				6
			],
			[
				0,
				5,
				6,
				4,
				6
			],
			[
				0,
				4,
				6,
				6,
				5
			]
		],
		[
			[
				0,
				0,
				0,
				1,
				0
			],
			[
				0,
				2,
				5,
				8,
				2
			],
			[
				0,
				5,
				6,
				4,
				6
			],
			[
				1,
				8,
				4,
				4,
				8
			],
			[
				0,
				2,
				6,
				8,
				7
			]
		],
		[
			[
				0,
				0,
				0,
				0,
				1
			],
			[
				0,
				2,
				4,
				2,
				9
			],
			[
				0,
				4,
				6,
				6,
				5
			],
			[
				0,
				2,
				6,
				8,
				7
			],
			[
				1,
				9,
				5,
				7,
				4
			]
		]
	],
	"texnames":[
		"\\text{FR}^{5,9,0}_{81}"
	],
	"barcode":[
		1,
		0,
		0,
		0,
		0,
		0,
		1,
		0,
		0,
		0,
		0,
		0,
		1,
		0,
		0,
		0,
		0,
		0,
		1,
		0,
		0,
		0,
		0,
		0,
		1,
		0,
		1,
		0,
		0,
		0,
		1,
		8,
		2,
		2,
		2,
		0,
		2,
		9,
		2,
		4,
		0,
		2,
		2,
		8,
		5,
		0,
		2,
		4,
		5,
		4,
		0,
		0,
		1,
		0,
		0,
		0,
		2,
		9,
		2,
		4,
		1,
		9,
		4,
		7,
		5,
		0,
		2,
		7,
		8,
		6,
		0,
		4,
		5,
		6,
		6,
		0,
		0,
		0,
		1,
		0,
		0,
		2,
		2,
		8,
		5,
		0,
		2,
		7,
		8,
		6,
		1,
		8,
		8,
		4,
		4,
		0,
		5,
		6,
		4,
		6,
		0,
		0,
		0,
		0,
		1,
		0,
		2,
		4,
		5,
		4,
		0,
		4,
		5,
		6,
		6,
		0,
		5,
		6,
		4,
		6,
		1,
		4,
		6,
		6,
		2
	],
	"formal_code":[
		5,
		9,
		0,
		81
	],
	"tensor_product_decompositions":{
		"identifiers":[
			"formal_code"
		],
		"value":[]
	},
	"sub_fusion_rings":{
		"identifiers":[
			"injection",
			"formal_code"
		],
		"value":[]
	},
	"numeric_characters":[
		[
			[
				1.0,
				0
			],
			[
				1.5917755984224543e1,
				0
			],
			[
				1.9065843136116293e1,
				0
			],
			[
				2.1584111306712636e1,
				0
			],
			[
				2.1866499406931027e1,
				0
			]
		],
		[
			[
				1.0,
				0
			],
			[
				6.6683504475084385,
				0
			],
			[
				-0.5739270277474555,
				0
			],
			[
				2.5959643312292218,
				0
			],
			[
				-6.961990248122524,
				0
			]
		],
		[
			[
				1.0,
				0
			],
			[
				6.567899045261491,
				0
			],
			[
				-2.2321910872764192,
				0
			],
			[
				-6.9848148147967475,
				0
			],
			[
				4.014058655400606,
				0
			]
		],
		[
			[
				1.0,
				0
			],
			[
				-9.957889035124975e-3,
				0
			],
			[
				-3.483056054019742,
				0
			],
			[
				1.8950751200892275,
				0
			],
			[
				1.1278620698480322,
				0
			]
		],
		[
			[
				1.0,
				0
			],
			[
				-0.14404758795934822,
				0
			],
			[
				0.2233310329273243,
				0
			],
			[
				-9.033594323433823e-2,
				0
			],
			[
				-4.6429884057140124e-2,
				0
			]
		]
	],
	"numeric_frobenius_perron_dimensions":[
		1.0,
		1.5917755984224542e1,
		1.9065843136116293e1,
		2.1584111306712636e1,
		2.1866499406931027e1
	],
	"numeric_frobenius_perron_dimension":1.5618989872781842e3,
	"info":"Fusion ring. mult_tab provides structure constants. barcode and formal_code provide unique identifiers see (DOI: 10.1063\/5.0148848). sub_fusion_rings provides tuples where the first element corresponds to the elements of the ring that form the subring isomorphic to the ring identified by the second element of the tuple. software provides doi of original software used to represent fusion ring.",
	"comments":[
		""
	]
}